examples/__init__.py
examples/car/__init__.py
examples/car/render.py
examples/car/run.py
examples/car/shared.py
examples/car/components/__init__.py
examples/car/components/mod0_cmp1.py
examples/car/components/mod1_cmp1.py
examples/car/components/mod2_cmp1.py
examples/car/components/mod2_cmp2.py
examples/car/components/mod3_cmp1.py
examples/car/components/shared.py
examples/car/components/shared2.py
examples/tanks/__init__.py
examples/tanks/render.py
examples/tanks/run.py
examples/tanks/run_price.py
examples/tanks/shared.py
examples/tanks/components/__init__.py
examples/tanks/components/mod1.py
examples/tanks/components/revenue.py
examples/tanks/components/unit_price.py
examples/wall/__init__.py
examples/wall/render.py
examples/wall/run_min_temperature.py
examples/wall/run_precompute.py
examples/wall/run_queries.py
examples/wall/run_set_results.py
examples/wall/run_sweep.py
examples/wall/utils.py
hubit/__init__.py
hubit/config.py
hubit/errors.py
hubit/model.py
hubit/qrun.py
hubit/render.py
hubit/tree.py
hubit/utils.py
hubit/worker.py
tests/__init__.py
tests/config_test.py
tests/model_test.py
tests/qrun_test.py
tests/shared_data.py
tests/tree_test.py
tests/utils_test.py
tests/worker_test.py
hubit-0.5.0.dist-info/LICENSE.md
hubit-0.5.0.dist-info/METADATA
hubit-0.5.0.dist-info/WHEEL
hubit-0.5.0.dist-info/top_level.txt
hubit-0.5.0.dist-info/RECORD
