Metadata-Version: 2.1
Name: hubit
Version: 0.5.0
Summary: Minimal tool for connecting your existing models in a composite model allowing for asynchronous multi-processed execution
Home-page: https://github.com/mrsonne/hubit
Author: Jacob Sonne
Author-email: mrsonne@gmail.com
License: BSD 3-Clause License
Keywords: model,hub,multi-process,asynchronous
Platform: UNKNOWN
Classifier: Development Status :: 3 - Alpha
Classifier: Intended Audience :: Developers
Classifier: License :: OSI Approved :: BSD License
Classifier: Operating System :: OS Independent
Classifier: Programming Language :: Python
Classifier: Programming Language :: Python :: 3.7
Classifier: Programming Language :: Python :: 3.8
Classifier: Programming Language :: Python :: 3.9
Classifier: Topic :: Software Development :: Libraries :: Python Modules
License-File: LICENSE.md
Requires-Dist: pyyaml
Requires-Dist: graphviz
Requires-Dist: python-version (>="3.8")
Provides-Extra: dev
Requires-Dist: coverage ; extra == 'dev'
Requires-Dist: black ; extra == 'dev'
Requires-Dist: coveralls ; extra == 'dev'
Requires-Dist: mypy ; extra == 'dev'
Requires-Dist: types-PyYAML ; extra == 'dev'
Requires-Dist: pytest ; extra == 'dev'
Requires-Dist: typing-extensions ; extra == 'dev'
